CMakeLists.txt
LICENSE.txt
MANIFEST.in
README.md
setup.py
pypims/CMakeLists.txt
pypims/__init__.py
pypims/version.py
pypims.egg-info/PKG-INFO
pypims.egg-info/SOURCES.txt
pypims.egg-info/dependency_links.txt
pypims.egg-info/not-zip-safe
pypims.egg-info/requires.txt
pypims.egg-info/top_level.txt
pypims/IO/Boundary.py
pypims/IO/InputHipims.py
pypims/IO/Landcover.py
pypims/IO/OutputHipims.py
pypims/IO/Rainfall.py
pypims/IO/Raster.py
pypims/IO/Summary.py
pypims/IO/__init__.py
pypims/IO/demo_functions.py
pypims/IO/grid_show.py
pypims/IO/indep_functions.py
pypims/IO/rainfall_processing.py
pypims/IO/spatial_analysis.py
pypims/IO/sample/DEM.gz
pypims/IO/sample/domain_map.png
pypims/IO/sample/landcover.gz
pypims/IO/sample/rain_mask.gz
pypims/IO/sample/rain_source.csv
pypims/apps/cudaFloodSolversPybind/CMakeLists.txt
pypims/apps/cudaFloodSolversPybind/cuda_flood_solvers.cu
pypims/apps/cudaFloodSolversPybind/cuda_flood_solvers.h
pypims/apps/cudaFloodSolversPybind/flood_solvers_pybind.cc
pypims/lib/CMakeLists.txt
pypims/lib/include/IO/cuda_backup_writer.h
pypims/lib/include/IO/cuda_gauges_writer.h
pypims/lib/include/IO/cuda_gisascii_writer.h
pypims/lib/include/IO/cuda_simple_writer.h
pypims/lib/include/IO/field_reader.h
pypims/lib/include/IO/gisAsciiField_reader.h
pypims/lib/include/IO/gisAsciiMesh_reader.h
pypims/lib/include/IO/gmsh_reader.h
pypims/lib/include/IO/mesh_reader.h
pypims/lib/include/IO/simple_writer.h
pypims/lib/include/archived/boundary/boundary.h
pypims/lib/include/archived/boundary/boundary_func_table.h
pypims/lib/include/archived/matrix/matrix.h
pypims/lib/include/archived/operators/CUDA_practice.h
pypims/lib/include/archived/operators/calculate_velocity.h
pypims/lib/include/archived/operators/ddt.h
pypims/lib/include/archived/operators/fluxBalanced_NSWEs.h
pypims/lib/include/archived/operators/fluxBalanced_SWEs.h
pypims/lib/include/archived/operators/fluxNonUniGravity_SWEs.h
pypims/lib/include/archived/operators/flux_SWEs.h
pypims/lib/include/archived/operators/modify_gravity.h
pypims/lib/include/archived/operators/modify_gravityAdvanced.h
pypims/lib/include/archived/operators/small_depth_filter.h
