Metadata-Version: 2.1
Name: pypims
Version: 0.0.3.1
Summary: Python APIs for hipims
Author: Xilin Xia
Author-email: x.xia2@lboro.ac.uk
License: GPLv3
Platform: UNKNOWN
Classifier: Development Status :: 3 - Alpha
Classifier: License :: OSI Approved :: GNU General Public License v3 or later (GPLv3+)
Classifier: Programming Language :: Python :: 3.7
Classifier: Programming Language :: C++
Classifier: Intended Audience :: Science/Research
License-File: LICENSE.txt
